delivery/phase1_rtl/pwm_ctrl.v
module pwm_ctrl (
  input        clk,
  input        rst,
  input  [7:0] duty,
  output       pwm_out
);
  reg [7:0] counter;

  always @(posedge clk) begin
    if (rst)
      counter <= 8'd0;
    else
      counter <= counter + 8'd1;  // 自动溢出回绕
  end

  assign pwm_out = (counter < duty);

endmodule

phase2_sim/tb/tb_pwm.v
// tb/tb_pwm.v
module tb_pwm;
  reg clk = 0, rst = 1;
  reg [7:0] duty = 8'd0;
  wire pwm_out;

  pwm_ctrl dut (
    .clk(clk), .rst(rst),
    .duty(duty), .pwm_out(pwm_out)
  );

  always #5 clk = ~clk;  // 100MHz

  integer high_count;
  integer total_count;
  integer test_pass;
  real measured_pct;
  real expected_pct;
  real pct_error;
  real tolerance_pct;

  task check_duty_cycle;
    input [7:0] expected_duty;
    input [31:0] cycles;
    begin
      high_count = 0;
      total_count = 0;
      repeat (cycles) begin
        @(posedge clk);
        #1;  // delta delay for signal stabilization after posedge clk
        total_count = total_count + 1;
        if (pwm_out) high_count = high_count + 1;
      end
      measured_pct = (100.0 * high_count) / total_count;
      expected_pct = (100.0 * expected_duty) / 256.0;
      pct_error = measured_pct - expected_pct;
      if (pct_error < 0.0) pct_error = -pct_error;
      $display("  duty=%0d: high=%0d/%0d (%.1f%%)", expected_duty,
               high_count, total_count,
               measured_pct);

      if (pct_error > tolerance_pct) begin
        $display("  FAIL: expected %.2f%%, measured %.2f%%, error %.2f%% > tolerance %.2f%%",
                 expected_pct, measured_pct, pct_error, tolerance_pct);
        test_pass = 0;
      end else begin
        $display("  PASS: expected %.2f%%, measured %.2f%%, error %.2f%%",
                 expected_pct, measured_pct, pct_error);
      end
    end
  endtask

  initial begin
    $dumpfile("wave.vcd"); $dumpvars;
    test_pass = 1;
    tolerance_pct = 0.5;  // With 256-cycle window, quantization error is <= 0.39%.

    // Test 1: Reset behavior
    $display("[TEST 1] Reset behavior");
    #20;
    if (pwm_out !== 1'b0) begin
      $display("  FAIL: pwm_out should be 0 during reset");
      test_pass = 0;
    end else begin
      $display("  PASS: pwm_out is 0 during reset");
    end

    // Release reset
    rst = 0;

    // Test 2: 50% duty cycle
    $display("[TEST 2] 50%% duty cycle (duty=128)");
    duty = 8'd128;
    check_duty_cycle(128, 256);

    // Test 3: 25% duty cycle
    $display("[TEST 3] 25%% duty cycle (duty=64)");
    duty = 8'd64;
    check_duty_cycle(64, 256);

    // Test 4: 0% duty cycle
    $display("[TEST 4] 0%% duty cycle (duty=0)");
    duty = 8'd0;
    check_duty_cycle(0, 256);

    // Test 5: ~100% duty cycle
    $display("[TEST 5] ~100%% duty cycle (duty=255)");
    duty = 8'd255;
    check_duty_cycle(255, 256);

    // Test 6: Reset during operation
    $display("[TEST 6] Reset during operation");
    duty = 8'd0;
    #100;  // wait ~10 clock cycles at 100MHz before asserting reset
    rst = 1;
    @(posedge clk); #1;
    if (pwm_out !== 1'b0) begin
      $display("  FAIL: pwm_out should be 0 during reset (with duty=0)");
      test_pass = 0;
    end else begin
      $display("  PASS: counter reset confirmed, pwm_out is 0");
    end
    rst = 0;
    duty = 8'd128;
    check_duty_cycle(128, 256);

    if (test_pass) begin
      $display("\n=== ALL TESTS PASSED ===");
      $finish_and_return(0);
    end else begin
      $display("\n=== SOME TESTS FAILED ===");
      $finish_and_return(1);
    end

    $finish;
  end
endmodule

delivery/phase2_sim/wave.vcd
$date
	Tue May  5 08:23:56 2026
$end
$version
	Icarus Verilog
$end
$timescale
	1s
$end
$scope module tb_pwm $end
$var wire 1 ! pwm_out $end
$var reg 1 " clk $end
$var reg 8 # duty [7:0] $end
$var reg 1 $ rst $end
$var real 1 % expected_pct $end
$var integer 32 & high_count [31:0] $end
$var real 1 ' measured_pct $end
$var real 1 ( pct_error $end
$var integer 32 ) test_pass [31:0] $end
$var real 1 * tolerance_pct $end
$var integer 32 + total_count [31:0] $end
$scope module dut $end
$var wire 1 " clk $end
$var wire 8 , duty [7:0] $end
$var wire 1 $ rst $end
$var wire 1 ! pwm_out $end
$var reg 8 - counter [7:0] $end
$upscope $end
$scope task check_duty_cycle $end
$var reg 32 . cycles [31:0] $end
$var reg 8 / expected_duty [7:0] $end
$upscope $end
$upscope $end
$enddefinitions $end
$comment Show the parameter values. $end
$dumpall
$end
#0
$dumpvars
bx /
bx .
bx -
b0 ,
bx +
r0.5 *
b1 )
r0 (
r0 '
bx &
r0 %
1$
b0 #
0"
x!
$end
#5
0!
b0 -
1"
#10
0"
#15
1"
#20
0"
b0 +
b0 &
b100000000 .
b10000000 /
1!
b10000000 #
b10000000 ,
0$
#25
b1 -
1"
#26
b1 &
b1 +
#30
0"
#35
b10 -
1"
#36
b10 &
b10 +
#40
0"
#45
b11 -
1"
#46
b11 &
b11 +
#50
0"
#55
b100 -
1"
#56
b100 &
b100 +
#60
0"
#65
b101 -
1"
#66
b101 &
b101 +
#70
0"
#75
b110 -
1"
#76
b110 &
b110 +
#80
0"
#85
b111 -
1"
#86
b111 &
b111 +
#90
0"
#95
b1000 -
1"
#96
b1000 &
b1000 +
#100
0"
#105
b1001 -
1"
#106
b1001 &
b1001 +
#110
0"
#115
b1010 -
1"
#116
b1010 &
b1010 +
#120
0"
#125
b1011 -
1"
#126
b1011 &
b1011 +
#130
0"
#135
b1100 -
1"
#136
b1100 &
b1100 +
#140
0"
#145
b1101 -
1"
#146
b1101 &
b1101 +
#150
0"
#155
b1110 -
1"
#156
b1110 &
b1110 +
#160
0"
#165
b1111 -
1"
#166
b1111 &
b1111 +
#170
0"
#175
b10000 -
1"
#176
b10000 &
b10000 +
#180
0"
#185
b10001 -
1"
#186
b10001 &
b10001 +
#190
0"
#195
b10010 -
1"
#196
b10010 &
b10010 +
#200
0"
#205
b10011 -
1"
#206
b10011 &
b10011 +
#210
0"
#215
b10100 -
1"
#216
b10100 &
b10100 +
#220
0"
#225
b10101 -
1"
#226
b10101 &
b10101 +
#230
0"
#235
b10110 -
1"
#236
b10110 &
b10110 +
#240
0"
#245
b10111 -
1"
#246
b10111 &
b10111 +
#250
0"
#255
b11000 -
1"
#256
b11000 &
b11000 +
#260
0"
#265
b11001 -
1"
#266
b11001 &
b11001 +
#270
0"
#275
b11010 -
1"
#276
b11010 &
b11010 +
#280
0"
#285
b11011 -
1"
#286
b11011 &
b11011 +
#290
0"
#295
b11100 -
1"
#296
b11100 &
b11100 +
#300
0"
#305
b11101 -
1"
#306
b11101 &
b11101 +
#310
0"
#315
b11110 -
1"
#316
b11110 &
b11110 +
#320
0"
#325
b11111 -
1"
#326
b11111 &
b11111 +
#330
0"
#335
b100000 -
1"
#336
b100000 &
b100000 +
#340
0"
#345
b100001 -
1"
#346
b100001 &
b100001 +
#350
0"
#355
b100010 -
1"
#356
b100010 &
b100010 +
#360
0"
#365
b100011 -
1"
#366
b100011 &
b100011 +
#370
0"
#375
b100100 -
1"
#376
b100100 &
b100100 +
#380
0"
#385
b100101 -
1"
#386
b100101 &
b100101 +
#390
0"
#395
b100110 -
1"
#396
b100110 &
b100110 +
#400
0"
#405
b100111 -
1"
#406
b100111 &
b100111 +
#410
0"
#415
b101000 -
1"
#416
b101000 &
b101000 +
#420
0"
#425
b101001 -
1"
#426
b101001 &
b101001 +
#430
0"
#435
b101010 -
1"
#436
b101010 &
b101010 +
#440
0"
#445
b101011 -
1"
#446
b101011 &
b101011 +
#450
0"
#455
b101100 -
1"
#456
b101100 &
b101100 +
#460
0"
#465
b101101 -
1"
#466
b101101 &
b101101 +
#470
0"
#475
b101110 -
1"
#476
b101110 &
b101110 +
#480
0"
#485
b101111 -
1"
#486
b101111 &
b101111 +
#490
0"
#495
b110000 -
1"
#496
b110000 &
b110000 +
#500
0"
#505
b110001 -
1"
#506
b110001 &
b110001 +
#510
0"
#515
b110010 -
1"
#516
b110010 &
b110010 +
#520
0"
#525
b110011 -
1"
#526
b110011 &
b110011 +
#530
0"
#535
b110100 -
1"
#536
b110100 &
b110100 +
#540
0"
#545
b110101 -
1"
#546
b110101 &
b110101 +
#550
0"
#555
b110110 -
1"
#556
b110110 &
b110110 +
#560
0"
#565
b110111 -
1"
#566
b110111 &
b110111 +
#570
0"
#575
b111000 -
1"
#576
b111000 &
b111000 +
#580
0"
#585
b111001 -
1"
#586
b111001 &
b111001 +
#590
0"
#595
b111010 -
1"
#596
b111010 &
b111010 +
#600
0"
#605
b111011 -
1"
#606
b111011 &
b111011 +
#610
0"
#615
b111100 -
1"
#616
b111100 &
b111100 +
#620
0"
#625
b111101 -
1"
#626
b111101 &
b111101 +
#630
0"
#635
b111110 -
1"
#636
b111110 &
b111110 +
#640
0"
#645
b111111 -
1"
#646
b111111 &
b111111 +
#650
0"
#655
b1000000 -
1"
#656
b1000000 &
b1000000 +
#660
0"
#665
b1000001 -
1"
#666
b1000001 &
b1000001 +
#670
0"
#675
b1000010 -
1"
#676
b1000010 &
b1000010 +
#680
0"
#685
b1000011 -
1"
#686
b1000011 &
b1000011 +
#690
0"
#695
b1000100 -
1"
#696
b1000100 &
b1000100 +
#700
0"
#705
b1000101 -
1"
#706
b1000101 &
b1000101 +
#710
0"
#715
b1000110 -
1"
#716
b1000110 &
b1000110 +
#720
0"
#725
b1000111 -
1"
#726
b1000111 &
b1000111 +
#730
0"
#735
b1001000 -
1"
#736
b1001000 &
b1001000 +
#740
0"
#745
b1001001 -
1"
#746
b1001001 &
b1001001 +
#750
0"
#755
b1001010 -
1"
#756
b1001010 &
b1001010 +
#760
0"
#765
b1001011 -
1"
#766
b1001011 &
b1001011 +
#770
0"
#775
b1001100 -
1"
#776
b1001100 &
b1001100 +
#780
0"
#785
b1001101 -
1"
#786
b1001101 &
b1001101 +
#790
0"
#795
b1001110 -
1"
#796
b1001110 &
b1001110 +
#800
0"
#805
b1001111 -
1"
#806
b1001111 &
b1001111 +
#810
0"
#815
b1010000 -
1"
#816
b1010000 &
b1010000 +
#820
0"
#825
b1010001 -
1"
#826
b1010001 &
b1010001 +
#830
0"
#835
b1010010 -
1"
#836
b1010010 &
b1010010 +
#840
0"
#845
b1010011 -
1"
#846
b1010011 &
b1010011 +
#850
0"
#855
b1010100 -
1"
#856
b1010100 &
b1010100 +
#860
0"
#865
b1010101 -
1"
#866
b1010101 &
b1010101 +
#870
0"
#875
b1010110 -
1"
#876
b1010110 &
b1010110 +
#880
0"
#885
b1010111 -
1"
#886
b1010111 &
b1010111 +
#890
0"
#895
b1011000 -
1"
#896
b1011000 &
b1011000 +
#900
0"
#905
b1011001 -
1"
#906
b1011001 &
b1011001 +
#910
0"
#915
b1011010 -
1"
#916
b1011010 &
b1011010 +
#920
0"
#925
b1011011 -
1"
#926
b1011011 &
b1011011 +
#930
0"
#935
b1011100 -
1"
#936
b1011100 &
b1011100 +
#940
0"
#945
b1011101 -
1"
#946
b1011101 &
b1011101 +
#950
0"
#955
b1011110 -
1"
#956
b1011110 &
b1011110 +
#960
0"
#965
b1011111 -
1"
#966
b1011111 &
b1011111 +
#970
0"
#975
b1100000 -
1"
#976
b1100000 &
b1100000 +
#980
0"
#985
b1100001 -
1"
#986
b1100001 &
b1100001 +
#990
0"
#995
b1100010 -
1"
#996
b1100010 &
b1100010 +
#1000
0"
#1005
b1100011 -
1"
#1006
b1100011 &
b1100011 +
#1010
0"
#1015
b1100100 -
1"
#1016
b1100100 &
b1100100 +
#1020
0"
#1025
b1100101 -
1"
#1026
b1100101 &
b1100101 +
#1030
0"
#1035
b1100110 -
1"
#1036
b1100110 &
b1100110 +
#1040
0"
#1045
b1100111 -
1"
#1046
b1100111 &
b1100111 +
#1050
0"
#1055
b1101000 -
1"
#1056
b1101000 &
b1101000 +
#1060
0"
#1065
b1101001 -
1"
#1066
b1101001 &
b1101001 +
#1070
0"
#1075
b1101010 -
1"
#1076
b1101010 &
b1101010 +
#1080
0"
#1085
b1101011 -
1"
#1086
b1101011 &
b1101011 +
#1090
0"
#1095
b1101100 -
1"
#1096
b1101100 &
b1101100 +
#1100
0"
#1105
b1101101 -
1"
#1106
b1101101 &
b1101101 +
#1110
0"
#1115
b1101110 -
1"
#1116
b1101110 &
b1101110 +
#1120
0"
#1125
b1101111 -
1"
#1126
b1101111 &
b1101111 +
#1130
0"
#1135
b1110000 -
1"
#1136
b1110000 &
b1110000 +
#1140
0"
#1145
b1110001 -
1"
#1146
b1110001 &
b1110001 +
#1150
0"
#1155
b1110010 -
1"
#1156
b1110010 &
b1110010 +
#1160
0"
#1165
b1110011 -
1"
#1166
b1110011 &
b1110011 +
#1170
0"
#1175
b1110100 -
1"
#1176
b1110100 &
b1110100 +
#1180
0"
#1185
b1110101 -
1"
#1186
b1110101 &
b1110101 +
#1190
0"
#1195
b1110110 -
1"
#1196
b1110110 &
b1110110 +
#1200
0"
#1205
b1110111 -
1"
#1206
b1110111 &
b1110111 +
#1210
0"
#1215
b1111000 -
1"
#1216
b1111000 &
b1111000 +
#1220
0"
#1225
b1111001 -
1"
#1226
b1111001 &
b1111001 +
#1230
0"
#1235
b1111010 -
1"
#1236
b1111010 &
b1111010 +
#1240
0"
#1245
b1111011 -
1"
#1246
b1111011 &
b1111011 +
#1250
0"
#1255
b1111100 -
1"
#1256
b1111100 &
b1111100 +
#1260
0"
#1265
b1111101 -
1"
#1266
b1111101 &
b1111101 +
#1270
0"
#1275
b1111110 -
1"
#1276
b1111110 &
b1111110 +
#1280
0"
#1285
b1111111 -
1"
#1286
b1111111 &
b1111111 +
#1290
0"
#1295
0!
b10000000 -
1"
#1296
b10000000 +
#1300
0"
#1305
b10000001 -
1"
#1306
b10000001 +
#1310
0"
#1315
b10000010 -
1"
#1316
b10000010 +
#1320
0"
#1325
b10000011 -
1"
#1326
b10000011 +
#1330
0"
#1335
b10000100 -
1"
#1336
b10000100 +
#1340
0"
#1345
b10000101 -
1"
#1346
b10000101 +
#1350
0"
#1355
b10000110 -
1"
#1356
b10000110 +
#1360
0"
#1365
b10000111 -
1"
#1366
b10000111 +
#1370
0"
#1375
b10001000 -
1"
#1376
b10001000 +
#1380
0"
#1385
b10001001 -
1"
#1386
b10001001 +
#1390
0"
#1395
b10001010 -
1"
#1396
b10001010 +
#1400
0"
#1405
b10001011 -
1"
#1406
b10001011 +
#1410
0"
#1415
b10001100 -
1"
#1416
b10001100 +
#1420
0"
#1425
b10001101 -
1"
#1426
b10001101 +
#1430
0"
#1435
b10001110 -
1"
#1436
b10001110 +
#1440
0"
#1445
b10001111 -
1"
#1446
b10001111 +
#1450
0"
#1455
b10010000 -
1"
#1456
b10010000 +
#1460
0"
#1465
b10010001 -
1"
#1466
b10010001 +
#1470
0"
#1475
b10010010 -
1"
#1476
b10010010 +
#1480
0"
#1485
b10010011 -
1"
#1486
b10010011 +
#1490
0"
#1495
b10010100 -
1"
#1496
b10010100 +
#1500
0"
#1505
b10010101 -
1"
#1506
b10010101 +
#1510
0"
#1515
b10010110 -
1"
#1516
b10010110 +
#1520
0"
#1525
b10010111 -
1"
#1526
b10010111 +
#1530
0"
#1535
b10011000 -
1"
#1536
b10011000 +
#1540
0"
#1545
b10011001 -
1"
#1546
b10011001 +
#1550
0"
#1555
b10011010 -
1"
#1556
b10011010 +
#1560
0"
#1565
b10011011 -
1"
#1566
b10011011 +
#1570
0"
#1575
b10011100 -
1"
#1576
b10011100 +
#1580
0"
#1585
b10011101 -
1"
#1586
b10011101 +
#1590
0"
#1595
b10011110 -
1"
#1596
b10011110 +
#1600
0"
#1605
b10011111 -
1"
#1606
b10011111 +
#1610
0"
#1615
b10100000 -
1"
#1616
b10100000 +
#1620
0"
#1625
b10100001 -
1"
#1626
b10100001 +
#1630
0"
#1635
b10100010 -
1"
#1636
b10100010 +
#1640
0"
#1645
b10100011 -
1"
#1646
b10100011 +
#1650
0"
#1655
b10100100 -
1"
#1656
b10100100 +
#1660
0"
#1665
b10100101 -
1"
#1666
b10100101 +
#1670
0"
#1675
b10100110 -
1"
#1676
b10100110 +
#1680
0"
#1685
b10100111 -
1"
#1686
b10100111 +
#1690
0"
#1695
b10101000 -
1"
#1696
b10101000 +
#1700
0"
#1705
b10101001 -
1"
#1706
b10101001 +
#1710
0"
#1715
b10101010 -
1"
#1716
b10101010 +
#1720
0"
#1725
b10101011 -
1"
#1726
b10101011 +
#1730
0"
#1735
b10101100 -
1"
#1736
b10101100 +
#1740
0"
#1745
b10101101 -
1"
#1746
b10101101 +
#1750
0"
#1755
b10101110 -
1"
#1756
b10101110 +
#1760
0"
#1765
b10101111 -
1"
#1766
b10101111 +
#1770
0"
#1775
b10110000 -
1"
#1776
b10110000 +
#1780
0"
#1785
b10110001 -
1"
#1786
b10110001 +
#1790
0"
#1795
b10110010 -
1"
#1796
b10110010 +
#1800
0"
#1805
b10110011 -
1"
#1806
b10110011 +
#1810
0"
#1815
b10110100 -
1"
#1816
b10110100 +
#1820
0"
#1825
b10110101 -
1"
#1826
b10110101 +
#1830
0"
#1835
b10110110 -
1"
#1836
b10110110 +
#1840
0"
#1845
b10110111 -
1"
#1846
b10110111 +
#1850
0"
#1855
b10111000 -
1"
#1856
b10111000 +
#1860
0"
#1865
b10111001 -
1"
#1866
b10111001 +
#1870
0"
#1875
b10111010 -
1"
#1876
b10111010 +
#1880
0"
#1885
b10111011 -
1"
#1886
b10111011 +
#1890
0"
#1895
b10111100 -
1"
#1896
b10111100 +
#1900
0"
#1905
b10111101 -
1"
#1906
b10111101 +
#1910
0"
#1915
b10111110 -
1"
#1916
b10111110 +
#1920
0"
#1925
b10111111 -
1"
#1926
b10111111 +
#1930
0"
#1935
b11000000 -
1"
#1936
b11000000 +
#1940
0"
#1945
b11000001 -
1"
#1946
b11000001 +
#1950
0"
#1955
b11000010 -
1"
#1956
b11000010 +
#1960
0"
#1965
b11000011 -
1"
#1966
b11000011 +
#1970
0"
#1975
b11000100 -
1"
#1976
b11000100 +
#1980
0"
#1985
b11000101 -
1"
#1986
b11000101 +
#1990
0"
#1995
b11000110 -
1"
#1996
b11000110 +
#2000
0"
#2005
b11000111 -
1"
#2006
b11000111 +
#2010
0"
#2015
b11001000 -
1"
#2016
b11001000 +
#2020
0"
#2025
b11001001 -
1"
#2026
b11001001 +
#2030
0"
#2035
b11001010 -
1"
#2036
b11001010 +
#2040
0"
#2045
b11001011 -
1"
#2046
b11001011 +
#2050
0"
#2055
b11001100 -
1"
#2056
b11001100 +
#2060
0"
#2065
b11001101 -
1"
#2066
b11001101 +
#2070
0"
#2075
b11001110 -
1"
#2076
b11001110 +
#2080
0"
#2085
b11001111 -
1"
#2086
b11001111 +
#2090
0"
#2095
b11010000 -
1"
#2096
b11010000 +
#2100
0"
#2105
b11010001 -
1"
#2106
b11010001 +
#2110
0"
#2115
b11010010 -
1"
#2116
b11010010 +
#2120
0"
#2125
b11010011 -
1"
#2126
b11010011 +
#2130
0"
#2135
b11010100 -
1"
#2136
b11010100 +
#2140
0"
#2145
b11010101 -
1"
#2146
b11010101 +
#2150
0"
#2155
b11010110 -
1"
#2156
b11010110 +
#2160
0"
#2165
b11010111 -
1"
#2166
b11010111 +
#2170
0"
#2175
b11011000 -
1"
#2176
b11011000 +
#2180
0"
#2185
b11011001 -
1"
#2186
b11011001 +
#2190
0"
#2195
b11011010 -
1"
#2196
b11011010 +
#2200
0"
#2205
b11011011 -
1"
#2206
b11011011 +
#2210
0"
#2215
b11011100 -
1"
#2216
b11011100 +
#2220
0"
#2225
b11011101 -
1"
#2226
b11011101 +
#2230
0"
#2235
b11011110 -
1"
#2236
b11011110 +
#2240
0"
#2245
b11011111 -
1"
#2246
b11011111 +
#2250
0"
#2255
b11100000 -
1"
#2256
b11100000 +
#2260
0"
#2265
b11100001 -
1"
#2266
b11100001 +
#2270
0"
#2275
b11100010 -
1"
#2276
b11100010 +
#2280
0"
#2285
b11100011 -
1"
#2286
b11100011 +
#2290
0"
#2295
b11100100 -
1"
#2296
b11100100 +
#2300
0"
#2305
b11100101 -
1"
#2306
b11100101 +
#2310
0"
#2315
b11100110 -
1"
#2316
b11100110 +
#2320
0"
#2325
b11100111 -
1"
#2326
b11100111 +
#2330
0"
#2335
b11101000 -
1"
#2336
b11101000 +
#2340
0"
#2345
b11101001 -
1"
#2346
b11101001 +
#2350
0"
#2355
b11101010 -
1"
#2356
b11101010 +
#2360
0"
#2365
b11101011 -
1"
#2366
b11101011 +
#2370
0"
#2375
b11101100 -
1"
#2376
b11101100 +
#2380
0"
#2385
b11101101 -
1"
#2386
b11101101 +
#2390
0"
#2395
b11101110 -
1"
#2396
b11101110 +
#2400
0"
#2405
b11101111 -
1"
#2406
b11101111 +
#2410
0"
#2415
b11110000 -
1"
#2416
b11110000 +
#2420
0"
#2425
b11110001 -
1"
#2426
b11110001 +
#2430
0"
#2435
b11110010 -
1"
#2436
b11110010 +
#2440
0"
#2445
b11110011 -
1"
#2446
b11110011 +
#2450
0"
#2455
b11110100 -
1"
#2456
b11110100 +
#2460
0"
#2465
b11110101 -
1"
#2466
b11110101 +
#2470
0"
#2475
b11110110 -
1"
#2476
b11110110 +
#2480
0"
#2485
b11110111 -
1"
#2486
b11110111 +
#2490
0"
#2495
b11111000 -
1"
#2496
b11111000 +
#2500
0"
#2505
b11111001 -
1"
#2506
b11111001 +
#2510
0"
#2515
b11111010 -
1"
#2516
b11111010 +
#2520
0"
#2525
b11111011 -
1"
#2526
b11111011 +
#2530
0"
#2535
b11111100 -
1"
#2536
b11111100 +
#2540
0"
#2545
b11111101 -
1"
#2546
b11111101 +
#2550
0"
#2555
b11111110 -
1"
#2556
b11111110 +
#2560
0"
#2565
b11111111 -
1"
#2566
b11111111 +
#2570
0"
#2575
1!
b0 -
1"
#2576
b1000000 /
b1000000 #
b1000000 ,
r50 %
r50 '
b0 &
b0 +
#2580
0"
#2585
b1 -
1"
#2586
b1 &
b1 +
#2590
0"
#2595
b10 -
1"
#2596
b10 &
b10 +
#2600
0"
#2605
b11 -
1"
#2606
b11 &
b11 +
#2610
0"
#2615
b100 -
1"
#2616
b100 &
b100 +
#2620
0"
#2625
b101 -
1"
#2626
b101 &
b101 +
#2630
0"
#2635
b110 -
1"
#2636
b110 &
b110 +
#2640
0"
#2645
b111 -
1"
#2646
b111 &
b111 +
#2650
0"
#2655
b1000 -
1"
#2656
b1000 &
b1000 +
#2660
0"
#2665
b1001 -
1"
#2666
b1001 &
b1001 +
#2670
0"
#2675
b1010 -
1"
#2676
b1010 &
b1010 +
#2680
0"
#2685
b1011 -
1"
#2686
b1011 &
b1011 +
#2690
0"
#2695
b1100 -
1"
#2696
b1100 &
b1100 +
#2700
0"
#2705
b1101 -
1"
#2706
b1101 &
b1101 +
#2710
0"
#2715
b1110 -
1"
#2716
b1110 &
b1110 +
#2720
0"
#2725
b1111 -
1"
#2726
b1111 &
b1111 +
#2730
0"
#2735
b10000 -
1"
#2736
b10000 &
b10000 +
#2740
0"
#2745
b10001 -
1"
#2746
b10001 &
b10001 +
#2750
0"
#2755
b10010 -
1"
#2756
b10010 &
b10010 +
#2760
0"
#2765
b10011 -
1"
#2766
b10011 &
b10011 +
#2770
0"
#2775
b10100 -
1"
#2776
b10100 &
b10100 +
#2780
0"
#2785
b10101 -
1"
#2786
b10101 &
b10101 +
#2790
0"
#2795
b10110 -
1"
#2796
b10110 &
b10110 +
#2800
0"
#2805
b10111 -
1"
#2806
b10111 &
b10111 +
#2810
0"
#2815
b11000 -
1"
#2816
b11000 &
b11000 +
#2820
0"
#2825
b11001 -
1"
#2826
b11001 &
b11001 +
#2830
0"
#2835
b11010 -
1"
#2836
b11010 &
b11010 +
#2840
0"
#2845
b11011 -
1"
#2846
b11011 &
b11011 +
#2850
0"
#2855
b11100 -
1"
#2856
b11100 &
b11100 +
#2860
0"
#2865
b11101 -
1"
#2866
b11101 &
b11101 +
#2870
0"
#2875
b11110 -
1"
#2876
b11110 &
b11110 +
#2880
0"
#2885
b11111 -
1"
#2886
b11111 &
b11111 +
#2890
0"
#2895
b100000 -
1"
#2896
b100000 &
b100000 +
#2900
0"
#2905
b100001 -
1"
#2906
b100001 &
b100001 +
#2910
0"
#2915
b100010 -
1"
#2916
b100010 &
b100010 +
#2920
0"
#2925
b100011 -
1"
#2926
b100011 &
b100011 +
#2930
0"
#2935
b100100 -
1"
#2936
b100100 &
b100100 +
#2940
0"
#2945
b100101 -
1"
#2946
b100101 &
b100101 +
#2950
0"
#2955
b100110 -
1"
#2956
b100110 &
b100110 +
#2960
0"
#2965
b100111 -
1"
#2966
b100111 &
b100111 +
#2970
0"
#2975
b101000 -
1"
#2976
b101000 &
b101000 +
#2980
0"
#2985
b101001 -
1"
#2986
b101001 &
b101001 +
#2990
0"
#2995
b101010 -
1"
#2996
b101010 &
b101010 +
#3000
0"
#3005
b101011 -
1"
#3006
b101011 &
b101011 +
#3010
0"
#3015
b101100 -
1"
#3016
b101100 &
b101100 +
#3020
0"
#3025
b101101 -
1"
#3026
b101101 &
b101101 +
#3030
0"
#3035
b101110 -
1"
#3036
b101110 &
b101110 +
#3040
0"
#3045
b101111 -
1"
#3046
b101111 &
b101111 +
#3050
0"
#3055
b110000 -
1"
#3056
b110000 &
b110000 +
#3060
0"
#3065
b110001 -
1"
#3066
b110001 &
b110001 +
#3070
0"
#3075
b110010 -
1"
#3076
b110010 &
b110010 +
#3080
0"
#3085
b110011 -
1"
#3086
b110011 &
b110011 +
#3090
0"
#3095
b110100 -
1"
#3096
b110100 &
b110100 +
#3100
0"
#3105
b110101 -
1"
#3106
b110101 &
b110101 +
#3110
0"
#3115
b110110 -
1"
#3116
b110110 &
b110110 +
#3120
0"
#3125
b110111 -
1"
#3126
b110111 &
b110111 +
#3130
0"
#3135
b111000 -
1"
#3136
b111000 &
b111000 +
#3140
0"
#3145
b111001 -
1"
#3146
b111001 &
b111001 +
#3150
0"
#3155
b111010 -
1"
#3156
b111010 &
b111010 +
#3160
0"
#3165
b111011 -
1"
#3166
b111011 &
b111011 +
#3170
0"
#3175
b111100 -
1"
#3176
b111100 &
b111100 +
#3180
0"
#3185
b111101 -
1"
#3186
b111101 &
b111101 +
#3190
0"
#3195
b111110 -
1"
#3196
b111110 &
b111110 +
#3200
0"
#3205
b111111 -
1"
#3206
b111111 &
b111111 +
#3210
0"
#3215
0!
b1000000 -
1"
#3216
b1000000 +
#3220
0"
#3225
b1000001 -
1"
#3226
b1000001 +
#3230
0"
#3235
b1000010 -
1"
#3236
b1000010 +
#3240
0"
#3245
b1000011 -
1"
#3246
b1000011 +
#3250
0"
#3255
b1000100 -
1"
#3256
b1000100 +
#3260
0"
#3265
b1000101 -
1"
#3266
b1000101 +
#3270
0"
#3275
b1000110 -
1"
#3276
b1000110 +
#3280
0"
#3285
b1000111 -
1"
#3286
b1000111 +
#3290
0"
#3295
b1001000 -
1"
#3296
b1001000 +
#3300
0"
#3305
b1001001 -
1"
#3306
b1001001 +
#3310
0"
#3315
b1001010 -
1"
#3316
b1001010 +
#3320
0"
#3325
b1001011 -
1"
#3326
b1001011 +
#3330
0"
#3335
b1001100 -
1"
#3336
b1001100 +
#3340
0"
#3345
b1001101 -
1"
#3346
b1001101 +
#3350
0"
#3355
b1001110 -
1"
#3356
b1001110 +
#3360
0"
#3365
b1001111 -
1"
#3366
b1001111 +
#3370
0"
#3375
b1010000 -
1"
#3376
b1010000 +
#3380
0"
#3385
b1010001 -
1"
#3386
b1010001 +
#3390
0"
#3395
b1010010 -
1"
#3396
b1010010 +
#3400
0"
#3405
b1010011 -
1"
#3406
b1010011 +
#3410
0"
#3415
b1010100 -
1"
#3416
b1010100 +
#3420
0"
#3425
b1010101 -
1"
#3426
b1010101 +
#3430
0"
#3435
b1010110 -
1"
#3436
b1010110 +
#3440
0"
#3445
b1010111 -
1"
#3446
b1010111 +
#3450
0"
#3455
b1011000 -
1"
#3456
b1011000 +
#3460
0"
#3465
b1011001 -
1"
#3466
b1011001 +
#3470
0"
#3475
b1011010 -
1"
#3476
b1011010 +
#3480
0"
#3485
b1011011 -
1"
#3486
b1011011 +
#3490
0"
#3495
b1011100 -
1"
#3496
b1011100 +
#3500
0"
#3505
b1011101 -
1"
#3506
b1011101 +
#3510
0"
#3515
b1011110 -
1"
#3516
b1011110 +
#3520
0"
#3525
b1011111 -
1"
#3526
b1011111 +
#3530
0"
#3535
b1100000 -
1"
#3536
b1100000 +
#3540
0"
#3545
b1100001 -
1"
#3546
b1100001 +
#3550
0"
#3555
b1100010 -
1"
#3556
b1100010 +
#3560
0"
#3565
b1100011 -
1"
#3566
b1100011 +
#3570
0"
#3575
b1100100 -
1"
#3576
b1100100 +
#3580
0"
#3585
b1100101 -
1"
#3586
b1100101 +
#3590
0"
#3595
b1100110 -
1"
#3596
b1100110 +
#3600
0"
#3605
b1100111 -
1"
#3606
b1100111 +
#3610
0"
#3615
b1101000 -
1"
#3616
b1101000 +
#3620
0"
#3625
b1101001 -
1"
#3626
b1101001 +
#3630
0"
#3635
b1101010 -
1"
#3636
b1101010 +
#3640
0"
#3645
b1101011 -
1"
#3646
b1101011 +
#3650
0"
#3655
b1101100 -
1"
#3656
b1101100 +
#3660
0"
#3665
b1101101 -
1"
#3666
b1101101 +
#3670
0"
#3675
b1101110 -
1"
#3676
b1101110 +
#3680
0"
#3685
b1101111 -
1"
#3686
b1101111 +
#3690
0"
#3695
b1110000 -
1"
#3696
b1110000 +
#3700
0"
#3705
b1110001 -
1"
#3706
b1110001 +
#3710
0"
#3715
b1110010 -
1"
#3716
b1110010 +
#3720
0"
#3725
b1110011 -
1"
#3726
b1110011 +
#3730
0"
#3735
b1110100 -
1"
#3736
b1110100 +
#3740
0"
#3745
b1110101 -
1"
#3746
b1110101 +
#3750
0"
#3755
b1110110 -
1"
#3756
b1110110 +
#3760
0"
#3765
b1110111 -
1"
#3766
b1110111 +
#3770
0"
#3775
b1111000 -
1"
